.gitignore
CHANGES.rst
MANIFEST.in
README.rst
README.txt
bootstrap.py
buildout.cfg
setup.py
docs/CREDITS.txt
docs/INSTALL.txt
docs/LICENSE.GPL
docs/LICENSE.txt
pas/__init__.py
pas.plugins.aselect.egg-info/PKG-INFO
pas.plugins.aselect.egg-info/SOURCES.txt
pas.plugins.aselect.egg-info/dependency_links.txt
pas.plugins.aselect.egg-info/entry_points.txt
pas.plugins.aselect.egg-info/namespace_packages.txt
pas.plugins.aselect.egg-info/not-zip-safe
pas.plugins.aselect.egg-info/requires.txt
pas.plugins.aselect.egg-info/top_level.txt
pas/plugins/__init__.py
pas/plugins/aselect/README.txt
pas/plugins/aselect/__init__.py
pas/plugins/aselect/aselectpas.py
pas/plugins/aselect/browser.txt
pas/plugins/aselect/config.py
pas/plugins/aselect/configure.zcml
pas/plugins/aselect/rebuild_i18n.sh
pas/plugins/aselect/setuphandlers.py
pas/plugins/aselect/tests.py
pas/plugins/aselect/utils.py
pas/plugins/aselect/browser/__init__.py
pas/plugins/aselect/browser/aselect.pt
pas/plugins/aselect/browser/aselect.py
pas/plugins/aselect/browser/configure.zcml
pas/plugins/aselect/browser/test.py
pas/plugins/aselect/browser/testcookies.pt
pas/plugins/aselect/locales/pas.plugins.aselect.pot
pas/plugins/aselect/locales/en/LC_MESSAGES/pas.plugins.aselect.mo
pas/plugins/aselect/locales/en/LC_MESSAGES/pas.plugins.aselect.po
pas/plugins/aselect/locales/nl/LC_MESSAGES/pas.plugins.aselect.mo
pas/plugins/aselect/locales/nl/LC_MESSAGES/pas.plugins.aselect.po
pas/plugins/aselect/profiles/default/metadata.xml
pas/plugins/aselect/profiles/default/pas_plugins_aselect_various.txt
pas/plugins/aselect/www/aselect.png
pas/plugins/aselect/www/aselect.png.metadata
pas/plugins/aselect/www/aselectpasAdd.zpt
pas/plugins/aselect/www/cookieMap.zpt