Metadata-Version: 1.0
Name: pas.plugins.aselect
Version: 1.5
Summary: PAS Plugin for authentication with A-Select
Home-page: https://github.com/zestsoftware/pas.plugins.aselect
Author: Zest Software
Author-email: info@zestsoftware.nl
License: GPL
Platform: UNKNOWN
Classifier: Framework :: Plone
Classifier: Framework :: Plone :: 3.3
Classifier: Framework :: Plone :: 4.0
Classifier: Framework :: Plone :: 4.1
Classifier: Framework :: Plone :: 4.2
Classifier: Framework :: Plone :: 4.3
Classifier: Intended Audience :: Developers
Classifier: License :: OSI Approved :: GNU General Public License (GPL)
